source_firebase_realtime_database/__init__.py
source_firebase_realtime_database/firebase_rtdb.py
source_firebase_realtime_database/run.py
source_firebase_realtime_database/source.py
source_firebase_realtime_database/spec.yaml
airbyte_source_firebase_realtime_database-0.1.48.dist-info/METADATA
airbyte_source_firebase_realtime_database-0.1.48.dist-info/WHEEL
airbyte_source_firebase_realtime_database-0.1.48.dist-info/entry_points.txt
airbyte_source_firebase_realtime_database-0.1.48.dist-info/RECORD
